NiukeQianduanGangweiMianshiZhentiBaodian20212022Fix1/README.md
NiukeQianduanGangweiMianshiZhentiBaodian20212022Fix1/__init__.py
NiukeQianduanGangweiMianshiZhentiBaodian20212022Fix1/__main__.py
NiukeQianduanGangweiMianshiZhentiBaodian20212022Fix1/file.epub
NiukeQianduanGangweiMianshiZhentiBaodian20212022Fix1/index.html
NiukeQianduanGangweiMianshiZhentiBaodian20212022Fix1/css/__init__.py
NiukeQianduanGangweiMianshiZhentiBaodian20212022Fix1/css/annotations.css
NiukeQianduanGangweiMianshiZhentiBaodian20212022Fix1/css/main.css
NiukeQianduanGangweiMianshiZhentiBaodian20212022Fix1/css/normalize.css
NiukeQianduanGangweiMianshiZhentiBaodian20212022Fix1/css/popup.css
NiukeQianduanGangweiMianshiZhentiBaodian20212022Fix1/font/__init__.py
NiukeQianduanGangweiMianshiZhentiBaodian20212022Fix1/font/fontello.eot
NiukeQianduanGangweiMianshiZhentiBaodian20212022Fix1/font/fontello.svg
NiukeQianduanGangweiMianshiZhentiBaodian20212022Fix1/font/fontello.ttf
NiukeQianduanGangweiMianshiZhentiBaodian20212022Fix1/font/fontello.woff
NiukeQianduanGangweiMianshiZhentiBaodian20212022Fix1/img/__init__.py
NiukeQianduanGangweiMianshiZhentiBaodian20212022Fix1/img/annotator-glyph-sprite.png
NiukeQianduanGangweiMianshiZhentiBaodian20212022Fix1/img/annotator-icon-sprite.png
NiukeQianduanGangweiMianshiZhentiBaodian20212022Fix1/img/apple-touch-icon.png
NiukeQianduanGangweiMianshiZhentiBaodian20212022Fix1/img/cancelfullscreen.png
NiukeQianduanGangweiMianshiZhentiBaodian20212022Fix1/img/close.png
NiukeQianduanGangweiMianshiZhentiBaodian20212022Fix1/img/fullscreen.png
NiukeQianduanGangweiMianshiZhentiBaodian20212022Fix1/img/loader.gif
NiukeQianduanGangweiMianshiZhentiBaodian20212022Fix1/img/menu-icon.png
NiukeQianduanGangweiMianshiZhentiBaodian20212022Fix1/img/save.png
NiukeQianduanGangweiMianshiZhentiBaodian20212022Fix1/img/saved.png
NiukeQianduanGangweiMianshiZhentiBaodian20212022Fix1/img/settings-s.png
NiukeQianduanGangweiMianshiZhentiBaodian20212022Fix1/img/settings.png
niuke_qianduan_gangwei_mianshi_zhenti_baodian_2021_2022_fix1-2025.3.25.0.dist-info/METADATA
niuke_qianduan_gangwei_mianshi_zhenti_baodian_2021_2022_fix1-2025.3.25.0.dist-info/WHEEL
niuke_qianduan_gangwei_mianshi_zhenti_baodian_2021_2022_fix1-2025.3.25.0.dist-info/entry_points.txt
niuke_qianduan_gangwei_mianshi_zhenti_baodian_2021_2022_fix1-2025.3.25.0.dist-info/top_level.txt
niuke_qianduan_gangwei_mianshi_zhenti_baodian_2021_2022_fix1-2025.3.25.0.dist-info/RECORD
